<?xml version="1.0" encoding="utf-8"?>
<!DOCTYPE hibernate-mapping PUBLIC "-//Hibernate/Hibernate Mapping DTD 3.0//EN"
"http://hibernate.sourceforge.net/hibernate-mapping-3.0.dtd">
<!-- 
    Mapping file autogenerated by MyEclipse Persistence Tools
-->
<hibernate-mapping>
    <class name="clt.com.cn.model.entity.Smsmsinfo" table="SMSMSINFO" dynamic-update="true" dynamic-insert="true">
        <id name="ilineid" type="java.lang.Integer">
            <column name="ilineid" precision="22" scale="0" />
            <generator class="sequence" >
            <param name="sequence">S_SmsInfoID</param>
            </generator>
        </id>
        <property name="dtdate" type="java.util.Date">
            <column name="dtdate" />
        </property>
        <property name="dtexpired" type="java.util.Date">
            <column name="dtexpired" />
        </property>
        <property name="vcuserno" type="java.lang.String">
            <column name="vcuserno" length="30" />
        </property>
        <property name="vcmemo" type="java.lang.String">
            <column name="vcmemo" length="200" />
        </property>
        <property name="dtsenddate" type="java.util.Date">
            <column name="dtsenddate" />
        </property>
        <property name="istatus" type="java.lang.Integer">
            <column name="istatus" />
        </property>
        <property name="vcmobile" type="java.lang.String">
            <column name="vcmobile" length="30" />
        </property>
        <property name="idriverid" type="java.lang.Integer">
            <column name="idriverid" />
        </property>
        <property name="icompanyid" type="java.lang.Integer">
            <column name="icompanyid" />
        </property>
        <property name="iflag" type="java.lang.Integer">
            <column name="iflag" />
        </property>
        <property name="boms" type="java.lang.Integer">
            <column name="boms" />
        </property>
    </class>
</hibernate-mapping>
